Metadata-Version: 1.0
Name: txWS
Version: 0.7.1.1
Summary: Twisted WebSockets wrapper
Home-page: http://github.com/MostAwesomeDude/txWS
Author: Corbin Simpson
Author-email: simpsoco@osuosl.org
License: MIT/X11
Platform: UNKNOWN
